direct_to_cartesian/DataFile.py
direct_to_cartesian/DataFileHandler.py
direct_to_cartesian/__init__.py
direct_to_cartesian/cli.py
tests/FileHandlerTest.py
tests/__init__.py
util/__init__.py
util/const_util/CONTCAR_AND_POSCAR_CONFIG.py
util/const_util/__init__.py
util/dictionary_index_util/BASIC_DATA_INDEX.py
util/dictionary_index_util/COORDINATE_INDEX.py
util/dictionary_index_util/__init__.py
cartesian_converter_for_vasp-0.0.3.dist-info/LICENSE
cartesian_converter_for_vasp-0.0.3.dist-info/METADATA
cartesian_converter_for_vasp-0.0.3.dist-info/WHEEL
cartesian_converter_for_vasp-0.0.3.dist-info/entry_points.txt
cartesian_converter_for_vasp-0.0.3.dist-info/top_level.txt
cartesian_converter_for_vasp-0.0.3.dist-info/RECORD
